bundle/__init__.py
bundle/_version.py
bundle/cli.py
bundle/ble/__init__.py
bundle/ble/cli.py
bundle/ble/device.py
bundle/ble/framing.py
bundle/ble/link.py
bundle/ble/manager.py
bundle/ble/scanner.py
bundle/ble/vendors.py
bundle/ble/data/company_identifiers.yaml
bundle/core/README.md
bundle/core/__init__.py
bundle/core/browser.py
bundle/core/data.py
bundle/core/downloader.py
bundle/core/entity.py
bundle/core/logger.py
bundle/core/platform.py
bundle/core/process.py
bundle/core/sockets.py
bundle/core/tracer.py
bundle/core/utils.py
bundle/pybind/README.md
bundle/pybind/__init__.py
bundle/pybind/cli.py
bundle/pybind/extension.py
bundle/pybind/pybind.py
bundle/pybind/plugins/__init__.py
bundle/pybind/plugins/base.py
bundle/pybind/resolved/__init__.py
bundle/pybind/resolved/module.py
bundle/pybind/resolved/pkgconfig.py
bundle/pybind/resolved/project.py
bundle/pybind/resolvers/__init__.py
bundle/pybind/resolvers/module.py
bundle/pybind/resolvers/pkgconfig.py
bundle/pybind/resolvers/project.py
bundle/pybind/services/__init__.py
bundle/pybind/services/cmake.py
bundle/pybind/services/pkgconfig.py
bundle/pybind/specs/__init__.py
bundle/pybind/specs/module.py
bundle/pybind/specs/pkgconfig.py
bundle/pybind/specs/project.py
bundle/scraper/__init__.py
bundle/scraper/cli.py
bundle/scraper/sites/__init__.py
bundle/scraper/sites/site_1337/__init__.py
bundle/scraper/sites/site_1337/browser.py
bundle/scraper/sites/site_1337/data.py
bundle/testing/README.md
bundle/testing/__init__.py
bundle/testing/cli.py
bundle/testing/tools/__init__.py
bundle/testing/tools/assertions.py
bundle/testing/tools/utils.py
bundle/testing/tools/decorators/__init__.py
bundle/testing/tools/decorators/cprofile.py
bundle/testing/tools/decorators/data.py
bundle/testing/tools/references/__init__.py
bundle/testing/tools/references/data.py
bundle/testing/tools/references/entity.py
bundle/website/README.md
bundle/website/__init__.py
bundle/website/cli.py
bundle/website/common/__init__.py
thebundle-1.4.0.dist-info/licenses/LICENSE
thebundle-1.4.0.dist-info/METADATA
thebundle-1.4.0.dist-info/WHEEL
thebundle-1.4.0.dist-info/entry_points.txt
thebundle-1.4.0.dist-info/top_level.txt
thebundle-1.4.0.dist-info/RECORD
