Metadata-Version: 2.4
Name: thebundle
Version: 1.4.0
Summary: Python TheBundle essential code.
Author-email: "M. Treglia" <horuselohim@gmail.com>
Requires-Python: >=3.10
License-File: LICENSE
Requires-Dist: zmq
Requires-Dist: tqdm
Requires-Dist: rich
Requires-Dist: toml
Requires-Dist: wheel
Requires-Dist: click
Requires-Dist: aiohttp
Requires-Dist: pybind11
Requires-Dist: tabulate
Requires-Dist: rich_click
Requires-Dist: requests
Requires-Dist: colorama
Requires-Dist: aiofiles
Requires-Dist: pydantic
Requires-Dist: jsonschema
Requires-Dist: asyncclick
Requires-Dist: playwright
Requires-Dist: setuptools
Requires-Dist: typing-extensions
Requires-Dist: tornado>=6.1; sys_platform == "win32"
Provides-Extra: test
Requires-Dist: pytest; extra == "test"
Requires-Dist: pytest-asyncio; extra == "test"
Requires-Dist: nest_asyncio; extra == "test"
Provides-Extra: dev
Requires-Dist: snakeviz; extra == "dev"
Provides-Extra: pypi
Requires-Dist: build; extra == "pypi"
Requires-Dist: twine; extra == "pypi"
Provides-Extra: ble
Requires-Dist: bleak>=0.22.1; extra == "ble"
Requires-Dist: pyyaml; extra == "ble"
Provides-Extra: youtube
Requires-Dist: pytubefix; extra == "youtube"
Requires-Dist: mutagen; extra == "youtube"
Requires-Dist: ffmpeg-python; extra == "youtube"
Provides-Extra: web
Requires-Dist: fastapi; extra == "web"
Requires-Dist: uvicorn[standard]; extra == "web"
Requires-Dist: websockets; extra == "web"
Requires-Dist: jinja2; extra == "web"
Requires-Dist: bleak>=0.22.1; extra == "web"
Requires-Dist: pyyaml; extra == "web"
Provides-Extra: all
Requires-Dist: pytest; extra == "all"
Requires-Dist: pytest-asyncio; extra == "all"
Requires-Dist: nest_asyncio; extra == "all"
Requires-Dist: snakeviz; extra == "all"
Requires-Dist: build; extra == "all"
Requires-Dist: twine; extra == "all"
Requires-Dist: pytubefix; extra == "all"
Requires-Dist: mutagen; extra == "all"
Requires-Dist: ffmpeg-python; extra == "all"
Requires-Dist: fastapi; extra == "all"
Requires-Dist: uvicorn[standard]; extra == "all"
Requires-Dist: websockets; extra == "all"
Dynamic: license-file
